swift_sim-1.1.0.dist-info/RECORD
swift_sim-1.1.0.dist-info/METADATA
swift_sim-1.1.0.dist-info/LICENSE
swift_sim-1.1.0.dist-info/top_level.txt
swift_sim-1.1.0.dist-info/WHEEL
swift/__init__.py
swift/SwiftElement.py
swift/SwiftRoute.py
swift/rtc.py
swift/Swift.py
swift/phys.cpython-38-x86_64-linux-gnu.so
swift/out/index.html
swift/out/404.html
swift/out/favicon.ico
swift/out/gif.worker.js
swift/out/_next/static/4505raTMHe4w9sCJLnohk/_buildManifest.js
swift/out/_next/static/4505raTMHe4w9sCJLnohk/_ssgManifest.js
swift/out/_next/static/css/891db4ca6fc7f160.css
swift/out/_next/static/css/b8e53514f8cd3ef4.css
swift/out/_next/static/chunks/509.a53518080c2ce023.js
swift/out/_next/static/chunks/polyfills-c67a75d1b6f99dc8.js
swift/out/_next/static/chunks/main-b1241a9a70bb7dcd.js
swift/out/_next/static/chunks/webpack-d72f726b1b78b625.js
swift/out/_next/static/chunks/124.3100673cd1725d26.js
swift/out/_next/static/chunks/framework-37f5df078e1d84d6.js
swift/out/_next/static/chunks/633.d1896a91e660b6a9.js
swift/out/_next/static/chunks/pages/index-0723cc3b940b78c7.js
swift/out/_next/static/chunks/pages/_app-a37dfc0c6eb112f1.js
swift/out/_next/static/chunks/pages/_error-e4f561a102d9bb14.js
swift/out/icons/pause.svg
swift/out/icons/realtime.svg
swift/out/icons/fasttime.svg
swift/out/icons/play.svg
swift/out/icons/startRender.svg
swift/out/icons/snap.svg
swift/out/icons/stopRender.svg
swift/core/phys.cpp
swift/core/linalg.h
swift/core/phys.h
swift/core/Eigen/Cholesky
swift/core/Eigen/MetisSupport
swift/core/Eigen/Sparse
swift/core/Eigen/Householder
swift/core/Eigen/Dense
swift/core/Eigen/SparseCholesky
swift/core/Eigen/Core
swift/core/Eigen/SPQRSupport
swift/core/Eigen/SparseLU
swift/core/Eigen/Eigen
swift/core/Eigen/Jacobi
swift/core/Eigen/Eigenvalues
swift/core/Eigen/LU
swift/core/Eigen/StdList
swift/core/Eigen/KLUSupport
swift/core/Eigen/SparseQR
swift/core/Eigen/UmfPackSupport
swift/core/Eigen/SuperLUSupport
swift/core/Eigen/PaStiXSupport
swift/core/Eigen/StdDeque
swift/core/Eigen/StdVector
swift/core/Eigen/CholmodSupport
swift/core/Eigen/QtAlignedMalloc
swift/core/Eigen/PardisoSupport
